Metadata-Version: 2.1
Name: urllitelib
Version: 1.0.1
Summary: Automatic proxy migration.
Author: Pain
Author-email: benjaminrodriguezshhh@proton.me
